qt_py_logs/__init__.py
qt_py_logs/logger.py
qt_py_logs-0.2.1.dist-info/METADATA
qt_py_logs-0.2.1.dist-info/WHEEL
qt_py_logs-0.2.1.dist-info/licenses/LICENSE
qt_py_logs-0.2.1.dist-info/RECORD
