Metadata-Version: 2.4
Name: qt-py-logs
Version: 0.2.1
Summary: python client for https://github.com/ausward/QTLogs
License: CC NC SA
License-File: LICENSE
Author: Austin
Author-email: 71802516+ausward@users.noreply.github.com
Requires-Python: >=3.8
Classifier: Development Status :: 4 - Beta
Classifier: Intended Audience :: Developers
Classifier: License :: Other/Proprietary License
Classifier: Programming Language :: Python :: 3
Classifier: Programming Language :: Python :: 3.8
Classifier: Programming Language :: Python :: 3.9
Classifier: Programming Language :: Python :: 3.10
Classifier: Programming Language :: Python :: 3.11
Classifier: Programming Language :: Python :: 3.12
Classifier: Topic :: System :: Logging
Requires-Dist: paho-mqtt (>=2.1.0)
Requires-Dist: pyyaml (>=6.0.1)
Requires-Dist: watchdog (>=4.0.1)
Project-URL: Bug Tracker, https://github.com/ausward/qt-py-logs/issues
Project-URL: Homepage, https://github.com/ausward/qt-py-logs
Project-URL: Repository, https://github.com/ausward/qt-py-logs
